mpv.py
fuocore/__init__.py
fuocore/aio_tcp_server.py
fuocore/dispatch.py
fuocore/library.py
fuocore/live_lyric.py
fuocore/lyric.py
fuocore/models.py
fuocore/player.py
fuocore/provider.py
fuocore/pubsub.py
fuocore/schemas.py
fuocore/thread_tcp_server.py
fuocore/utils.py
fuocore/local/__init__.py
fuocore/local/provider.py
fuocore/local/schemas.py
fuocore/netease/__init__.py
fuocore/netease/api.py
fuocore/netease/models.py
fuocore/netease/provider.py
fuocore/netease/schemas.py
fuocore/qqmusic/__init__.py
fuocore/qqmusic/api.py
fuocore/qqmusic/models.py
fuocore/qqmusic/provider.py
fuocore/xiami/__init__.py
fuocore/xiami/api.py
fuocore/xiami/models.py
fuocore/xiami/provider.py
fuocore/xiami/schemas.py
fuocore-2.1.dist-info/METADATA
fuocore-2.1.dist-info/RECORD
fuocore-2.1.dist-info/WHEEL
fuocore-2.1.dist-info/top_level.txt
