Metadata-Version: 2.1
Name: fuocore
Version: 2.1
Summary: feeluown core
Home-page: https://github.com/cosven/feeluown-core
Author: Cosven
Author-email: yinshaowen241@gmail.com
License: UNKNOWN
Keywords: media,player,api
Platform: UNKNOWN
Classifier: Development Status :: 3 - Alpha
Classifier: Programming Language :: Python :: 3.5
Classifier: Programming Language :: Python :: 3.6
Classifier: Programming Language :: Python :: 3.7
Classifier: Programming Language :: Python :: 3 :: Only
Requires-Dist: pycrypto (>=2.6.1)
Requires-Dist: requests
Requires-Dist: beautifulsoup4 (>=4.5.3)
Requires-Dist: marshmallow (>=2.13.5)
Requires-Dist: mutagen (>=1.37)
Requires-Dist: fuzzywuzzy
